{
  "type_description_msg": {
    "type_description": {
      "type_name": "rcl_interfaces/srv/GetParameterTypes",
      "fields": [
        {
          "name": "request_message",
          "type": {
            "type_id": 1,
            "capacity": 0,
            "string_capacity": 0,
            "nested_type_name": "rcl_interfaces/srv/GetParameterTypes_Request"
          },
          "default_value": ""
        },
        {
          "name": "response_message",
          "type": {
            "type_id": 1,
            "capacity": 0,
            "string_capacity": 0,
            "nested_type_name": "rcl_interfaces/srv/GetParameterTypes_Response"
          },
          "default_value": ""
        },
        {
          "name": "event_message",
          "type": {
            "type_id": 1,
            "capacity": 0,
            "string_capacity": 0,
            "nested_type_name": "rcl_interfaces/srv/GetParameterTypes_Event"
          },
          "default_value": ""
        }
      ]
    },
    "referenced_type_descriptions": [
      {
        "type_name": "builtin_interfaces/msg/Time",
        "fields": [
          {
            "name": "sec",
            "type": {
              "type_id": 6,
              "capacity": 0,
              "string_capacity": 0,
              "nested_type_name": ""
            },
            "default_value": ""
          },
          {
            "name": "nanosec",
            "type": {
              "type_id": 7,
              "capacity": 0,
              "string_capacity": 0,
              "nested_type_name": ""
            },
            "default_value": ""
          }
        ]
      },
      {
        "type_name": "rcl_interfaces/srv/GetParameterTypes_Event",
        "fields": [
          {
            "name": "info",
            "type": {
              "type_id": 1,
              "capacity": 0,
              "string_capacity": 0,
              "nested_type_name": "service_msgs/msg/ServiceEventInfo"
            },
            "default_value": ""
          },
          {
            "name": "request",
            "type": {
              "type_id": 97,
              "capacity": 1,
              "string_capacity": 0,
              "nested_type_name": "rcl_interfaces/srv/GetParameterTypes_Request"
            },
            "default_value": ""
          },
          {
            "name": "response",
            "type": {
              "type_id": 97,
              "capacity": 1,
              "string_capacity": 0,
              "nested_type_name": "rcl_interfaces/srv/GetParameterTypes_Response"
            },
            "default_value": ""
          }
        ]
      },
      {
        "type_name": "rcl_interfaces/srv/GetParameterTypes_Request",
        "fields": [
          {
            "name": "names",
            "type": {
              "type_id": 161,
              "capacity": 0,
              "string_capacity": 0,
              "nested_type_name": ""
            },
            "default_value": ""
          }
        ]
      },
      {
        "type_name": "rcl_interfaces/srv/GetParameterTypes_Response",
        "fields": [
          {
            "name": "types",
            "type": {
              "type_id": 147,
              "capacity": 0,
              "string_capacity": 0,
              "nested_type_name": ""
            },
            "default_value": ""
          }
        ]
      },
      {
        "type_name": "service_msgs/msg/ServiceEventInfo",
        "fields": [
          {
            "name": "event_type",
            "type": {
              "type_id": 3,
              "capacity": 0,
              "string_capacity": 0,
              "nested_type_name": ""
            },
            "default_value": ""
          },
          {
            "name": "stamp",
            "type": {
              "type_id": 1,
              "capacity": 0,
              "string_capacity": 0,
              "nested_type_name": "builtin_interfaces/msg/Time"
            },
            "default_value": ""
          },
          {
            "name": "client_gid",
            "type": {
              "type_id": 51,
              "capacity": 16,
              "string_capacity": 0,
              "nested_type_name": ""
            },
            "default_value": ""
          },
          {
            "name": "sequence_number",
            "type": {
              "type_id": 8,
              "capacity": 0,
              "string_capacity": 0,
              "nested_type_name": ""
            },
            "default_value": ""
          }
        ]
      }
    ]
  },
  "type_hashes": [
    {
      "type_name": "rcl_interfaces/srv/GetParameterTypes",
      "hash_string": "RIHS01_da199c878688b3e530bdfe3ca8f74cb9fa0c303101e980a9e8f260e25e1c80ca"
    },
    {
      "type_name": "builtin_interfaces/msg/Time",
      "hash_string": "RIHS01_b106235e25a4c5ed35098aa0a61a3ee9c9b18d197f398b0e4206cea9acf9c197"
    },
    {
      "type_name": "rcl_interfaces/srv/GetParameterTypes_Event",
      "hash_string": "RIHS01_9516adca0cc885d46a59c2362fb8eb5f4906b046518266f8c645b454b0dddc60"
    },
    {
      "type_name": "rcl_interfaces/srv/GetParameterTypes_Request",
      "hash_string": "RIHS01_87d7ec5ef545d4daa289d500025d31fb2437bc8b8365ca367161c4dac4be33fd"
    },
    {
      "type_name": "rcl_interfaces/srv/GetParameterTypes_Response",
      "hash_string": "RIHS01_ac1335dce67c478e669434f6ac2fbff34fcd529580f272d3006785ba8b54e47f"
    },
    {
      "type_name": "service_msgs/msg/ServiceEventInfo",
      "hash_string": "RIHS01_41bcbbe07a75c9b52bc96bfd5c24d7f0fc0a08c0cb7921b3373c5732345a6f45"
    }
  ]
}